aprespy/__init__.py
aprespy/app.py
aprespy/navigation_toolbar.py
aprespy/img/add.png
aprespy/img/default_axis.png
aprespy/img/diagonal.png
aprespy/img/guide.png
aprespy/input/__init__.py
aprespy/input/z.py
aprespy-2014.4.267.dist-info/METADATA
aprespy-2014.4.267.dist-info/WHEEL
aprespy-2014.4.267.dist-info/top_level.txt
aprespy-2014.4.267.dist-info/RECORD
