Metadata-Version: 2.1
Name: aprespy
Version: 2014.4.267
Summary: Tools for MT.
Home-page: https://github.com/chaytus/aprespy
Author: Brady Fry
Author-email: bradyfry@chaytus.com
License: MIT license
Keywords: aprespy
Platform: UNKNOWN
Classifier: Development Status :: 2 - Pre-Alpha
Classifier: Intended Audience :: Developers
Classifier: License :: OSI Approved :: MIT License
Classifier: Natural Language :: English
Classifier: Programming Language :: Python :: 3
Classifier: Programming Language :: Python :: 3.6
Classifier: Programming Language :: Python :: 3.7
Classifier: Programming Language :: Python :: 3.8
Requires-Python: >=3.6
Requires-Dist: matplotlib (>=3.3.2)
Requires-Dist: PyQt5 (>=5.14.4)
Requires-Dist: click (>=7.1.2)
Requires-Dist: numpy (>=1.18.3)
